agentica/__init__.py
agentica/agent.py
agentica/agent_session.py
agentica/cli.py
agentica/config.py
agentica/document.py
agentica/media.py
agentica/memory.py
agentica/memorydb.py
agentica/python_agent.py
agentica/react_agent.py
agentica/reasoning.py
agentica/run_response.py
agentica/template.py
agentica/version.py
agentica/workflow.py
agentica/workflow_session.py
agentica/emb/__init__.py
agentica/emb/azure_openai_emb.py
agentica/emb/base.py
agentica/emb/fireworks_emb.py
agentica/emb/genimi_emb.py
agentica/emb/hash_emb.py
agentica/emb/huggingface_emb.py
agentica/emb/ollama_emb.py
agentica/emb/openai_emb.py
agentica/emb/sentence_transformer_emb.py
agentica/emb/text2vec_emb.py
agentica/emb/together_emb.py
agentica/emb/word2vec_emb.py
agentica/emb/zhipuai_emb.py
agentica/file/__init__.py
agentica/file/base.py
agentica/file/csv.py
agentica/file/txt.py
agentica/knowledge/__init__.py
agentica/knowledge/base.py
agentica/knowledge/langchain_knowledge.py
agentica/knowledge/llamaindex_knowledge.py
agentica/mcp/__init__.py
agentica/mcp/client.py
agentica/mcp/config.py
agentica/mcp/server.py
agentica/model/__init__.py
agentica/model/base.py
agentica/model/base_audio_model.py
agentica/model/content.py
agentica/model/message.py
agentica/model/response.py
agentica/model/anthropic/__init__.py
agentica/model/anthropic/claude.py
agentica/model/aws/__init__.py
agentica/model/aws/api_client.py
agentica/model/aws/bedrock.py
agentica/model/aws/claude.py
agentica/model/azure/__init__.py
agentica/model/azure/openai_chat.py
agentica/model/cohere/__init__.py
agentica/model/cohere/chat.py
agentica/model/deepseek/__init__.py
agentica/model/deepseek/chat.py
agentica/model/doubao/__init__.py
agentica/model/doubao/chat.py
agentica/model/fireworks/__init__.py
agentica/model/fireworks/fireworks.py
agentica/model/google/__init__.py
agentica/model/google/gemini.py
agentica/model/google/gemini_openai.py
agentica/model/groq/__init__.py
agentica/model/groq/groq.py
agentica/model/huggingface/__init__.py
mseep_agentica-1.1.2.dist-info/licenses/LICENSE
mseep_agentica-1.1.2.dist-info/METADATA
mseep_agentica-1.1.2.dist-info/WHEEL
mseep_agentica-1.1.2.dist-info/entry_points.txt
mseep_agentica-1.1.2.dist-info/top_level.txt
mseep_agentica-1.1.2.dist-info/RECORD
